{"paths":{},"types":[],"uuids":["20BivhAyZJ2bZ9hOy0JOzo","7ftBhgsiRAa4MjeXD2bB7C","42wbiHSF1BMYx2m1o9x0hG","87OjEv1iFPMJOosVUtS0qq","693Q/7QxBIp4HEJxcj8d8+","d4MZxWkDJNRKKmQAzjSW0Y","ecpdLyjvZBwrvm+cedCcQy","b78vdflVhGQaywJccbwOhf","d7TtzKUZ1Jl5CKVmlnZlCp","a54+JR4utP66bDHbjVpk2F","a5LWeBMglABbx8Oq40wAB6","b3/7LCYl5NcbZaHnyD1f8Y"],"scenes":{"db://assets/jianjie/1.fire":0},"redirect":[6,0],"deps":["internal"],"packs":{"03c11e2fb":[0,10,9,11,7,8],"06d73811c":[2,4,1,3,5]},"name":"main","importBase":"import","nativeBase":"native","debug":false,"isZip":false,"encrypted":false,"versions":{"import":["03c11e2fb","42fd8","06d73811c","9b5a3"],"native":[2,"82ed3",4,"32d35",1,"85cac",3,"86ef2",5,"bfc68"]}}